base/__init__.py
base/cli.py
base/config.py
base/dataset.py
base/exception.py
base/files.py
base/hash.py
base/parser.py
base/project.py
base/spinner.py
adansons_base-0.1.3.dist-info/entry_points.txt
adansons_base-0.1.3.dist-info/LICENSE
adansons_base-0.1.3.dist-info/WHEEL
adansons_base-0.1.3.dist-info/METADATA
adansons_base-0.1.3.dist-info/RECORD
