Metadata-Version: 2.1
Name: adansons-base
Version: 0.1.3
Summary: Adansons Base
Home-page: https://github.com/adansons/base
License: MIT
Author: Adansons Developers
Author-email: engineer@adansons.co.jp
Requires-Python: >=3.8,<3.11
Classifier: Development Status :: 4 - Beta
Classifier: Intended Audience :: Developers
Classifier: Intended Audience :: Information Technology
Classifier: Intended Audience :: Science/Research
Classifier: License :: OSI Approved :: MIT License
Classifier: Operating System :: MacOS
Classifier: Operating System :: Microsoft :: Windows
Classifier: Operating System :: POSIX :: Linux
Classifier: Programming Language :: Python :: 3
Classifier: Programming Language :: Python :: 3.10
Classifier: Programming Language :: Python :: 3.8
Classifier: Programming Language :: Python :: 3.9
Classifier: Topic :: Database
Classifier: Topic :: Scientific/Engineering
Classifier: Topic :: Scientific/Engineering :: Artificial Intelligence
Classifier: Topic :: Scientific/Engineering :: Information Analysis
Requires-Dist: PyYAML (>=6.0,<7.0)
Requires-Dist: click (>=8.0.0)
Requires-Dist: colorama (>=0.4.4,<0.5.0)
Requires-Dist: numpy (>=1.18.5)
Requires-Dist: pandas (>=1.4.3,<2.0.0)
Requires-Dist: requests (>=1.0.0)
Requires-Dist: ruamel.yaml (>=0.17.21,<0.18.0)
Requires-Dist: scikit-learn (>=0.23.0)
Project-URL: Repository, https://github.com/adansons/base
